pydantic_metamodel/.DS_Store
pydantic_metamodel/__init__.py
pydantic_metamodel/__main__.py
pydantic_metamodel/api.py
pydantic_metamodel/cli.py
pydantic_metamodel/py.typed
pydantic_metamodel/version.py
pydantic_metamodel-0.0.6.dist-info/licenses/LICENSE
pydantic_metamodel-0.0.6.dist-info/WHEEL
pydantic_metamodel-0.0.6.dist-info/entry_points.txt
pydantic_metamodel-0.0.6.dist-info/METADATA
pydantic_metamodel-0.0.6.dist-info/RECORD
